{"MaritalStatus": {"0": {"YearIncome": {"2": {"Bigger&Equal": {"Num_ChildrenAtHome": {"4": {"Bigger&Equal": 3, "Smaller": {"Num_ChildrenAtHome": {"2": {"Bigger&Equal": {"Age": {"82": {"Bigger&Equal": {"YearIncome": {"5": {"Bigger&Equal": {"Num_ChildrenAtHome": {"2": {"Bigger&Equal": 1, "Smaller": 3}}}, "Smaller": {"Num_ChildrenAtHome": {"2": {"Bigger&Equal": 0, "Smaller": 0}}}}}}, "Smaller": {"YearIncome": {"4": {"Bigger&Equal": {"Num_ChildrenAtHome": {"2": {"Bigger&Equal": 0, "Smaller": 0}}}, "Smaller": {"Num_ChildrenAtHome": {"2": {"Bigger&Equal": 0, "Smaller": 0}}}}}}}}}, "Smaller": {"YearIncome": {"6": {"Bigger&Equal": {"Age": {"80": {"Bigger&Equal": 0, "Smaller": {"Num_ChildrenAtHome": {"0": {"Bigger&Equal": 0, "Smaller": 0}}}}}}, "Smaller": {"Age": {"30": {"Bigger&Equal": {"Num_ChildrenAtHome": {"0": {"Bigger&Equal": 0, "Smaller": 0}}}, "Smaller": {"Num_ChildrenAtHome": {"0": {"Bigger&Equal": 0, "Smaller": 0}}}}}}}}}}}}}}}, "Smaller": {"Num_ChildrenAtHome": {"2": {"Bigger&Equal": {"Age": {"38": {"Bigger&Equal": {"YearIncome": {"0": {"Bigger&Equal": 0, "Smaller": 0}}}, "Smaller": {"YearIncome": {"0": {"Bigger&Equal": 3, "Smaller": 3}}}}}}, "Smaller": {"Age": {"42": {"Bigger&Equal": {"YearIncome": {"0": {"Bigger&Equal": 0, "Smaller": 0}}}, "Smaller": {"YearIncome": {"0": {"Bigger&Equal": 0, "Smaller": 0}}}}}}}}}}}}, "1": {"Num_ChildrenAtHome": {"2": {"Bigger&Equal": {"Num_ChildrenAtHome": {"4": {"Bigger&Equal": {"Age": {"64": {"Bigger&Equal": {"YearIncome": {"2": {"Bigger&Equal": {"Num_ChildrenAtHome": {"4": {"Bigger&Equal": 0, "Smaller": 0}}}, "Smaller": 3}}}, "Smaller": 3}}}, "Smaller": {"Age": {"59": {"Bigger&Equal": {"YearIncome": {"4": {"Bigger&Equal": 0, "Smaller": {"Num_ChildrenAtHome": {"2": {"Bigger&Equal": 3, "Smaller": 3}}}}}}, "Smaller": {"YearIncome": {"6": {"Bigger&Equal": {"Num_ChildrenAtHome": {"2": {"Bigger&Equal": 3, "Smaller": 3}}}, "Smaller": {"Num_ChildrenAtHome": {"2": {"Bigger&Equal": 0, "Smaller": 0}}}}}}}}}}}}, "Smaller": {"Age": {"28": {"Bigger&Equal": {"YearIncome": {"4": {"Bigger&Equal": {"Num_ChildrenAtHome": {"0": {"Bigger&Equal": 0, "Smaller": 0}}}, "Smaller": {"Num_ChildrenAtHome": {"0": {"Bigger&Equal": 0, "Smaller": 0}}}}}}, "Smaller": {"YearIncome": {"4": {"Bigger&Equal": {"Num_ChildrenAtHome": {"0": {"Bigger&Equal": 0, "Smaller": 0}}}, "Smaller": {"Num_ChildrenAtHome": {"0": {"Bigger&Equal": 2, "Smaller": 2}}}}}}}}}}}}}}